my_collection/__init__.py
my_collection/collect_framework.py
my_collection/text.txt
my_collection/unique_char.py
my_collection-0.1.3.dist-info/METADATA
my_collection-0.1.3.dist-info/WHEEL
my_collection-0.1.3.dist-info/licenses/LICENSE
my_collection-0.1.3.dist-info/RECORD
