Metadata-Version: 2.4
Name: my-collection
Version: 0.1.3
Summary: A Python package for text processing and argument parsing
Project-URL: Homepage, https://git.foxminded.ua/liliia-shpytsia-mentoring/task-5-packaging
Project-URL: Issues, https://git.foxminded.ua/liliia-shpytsia-mentoring/task-5-packaging/-/issues
Author-email: Liliia Shpytsia <fioletowujsemizwetik@gmail.com>
License: MIT
License-File: LICENSE
Classifier: License :: OSI Approved :: MIT License
Classifier: Operating System :: OS Independent
Classifier: Programming Language :: Python :: 3
Classifier: Programming Language :: Python :: 3.10
Requires-Python: >=3.10
Requires-Dist: uv>=0.1.0
